__init__.py
main.py
api/__init__.py
api/controllers/__init__.py
api/controllers/text_extraction_controller.py
api/rest/__init__.py
api/rest/v1/__init__.py
api/rest/v1/routes/__init__.py
api/rest/v1/routes/health.py
application/services/__init__.py
application/services/text_extraction_service.py
config/__init__.py
config/configuration_profiles.py
config/dependencies.py
config/dependency_container_improved.py
config/service_registry.py
config/settings.py
config/environments/__init__.py
config/environments/development.py
config/environments/production.py
domain/text/__init__.py
domain/text/chunking_factory.py
domain/text/chunking_strategy.py
domain/text/text_processor.py
infrastructure/cache/aioredis_patch.py
infrastructure/cache/redis_client.py
infrastructure/cache/redis_client_custom.py
infrastructure/cache/redis_config.py
infrastructure/external/__init__.py
infrastructure/external/rapidapi_client.py
infrastructure/external/rapidapi_config.py
infrastructure/extractors/__init__.py
infrastructure/extractors/extractor_factory.py
infrastructure/extractors/file_extractor.py
infrastructure/nlp/spacy_processor.py
shared/__init__.py
shared/hof/__init__.py
shared/kernel/__init__.py
shared/kernel/use_case.py
shared/logging/__init__.py
shared/logging/error_tracker.py
shared/logging/logger.py
shared/middleware/__init__.py
shared/middleware/error_handler.py
shared/middleware/logging.py
shared/middleware/rate_limit.py
px_rfs_project-1.0.0.dist-info/METADATA
px_rfs_project-1.0.0.dist-info/WHEEL
px_rfs_project-1.0.0.dist-info/entry_points.txt
px_rfs_project-1.0.0.dist-info/top_level.txt
px_rfs_project-1.0.0.dist-info/RECORD
