Metadata-Version: 2.4
Name: px-rfs-project
Version: 1.0.0
Summary: RFS Framework 기반 엔터프라이즈 Python 애플리케이션
Author-email: Cosmos Team <dev@cosmos.com>
Project-URL: Homepage, https://github.com/cosmos-team/px-rfs-project
Project-URL: Documentation, https://cosmos-team.github.io/px-rfs-project/
Project-URL: Repository, https://github.com/cosmos-team/px-rfs-project.git
Project-URL: Bug Tracker, https://github.com/cosmos-team/px-rfs-project/issues
Project-URL: Changelog, https://github.com/cosmos-team/px-rfs-project/blob/main/CHANGELOG.md
Keywords: fastapi,rfs-framework,enterprise,api,cosmos
Classifier: Development Status :: 4 - Beta
Classifier: Intended Audience :: Developers
Classifier: License :: OSI Approved :: MIT License
Classifier: Programming Language :: Python :: 3
Classifier: Programming Language :: Python :: 3.10
Classifier: Programming Language :: Python :: 3.11
Classifier: Programming Language :: Python :: 3.12
Classifier: Framework :: FastAPI
Classifier: Topic :: Software Development :: Libraries :: Application Frameworks
Requires-Python: >=3.10
Requires-Dist: fastapi==0.115.0
Requires-Dist: uvicorn[standard]==0.30.6
Requires-Dist: pydantic==2.9.2
Requires-Dist: pydantic-settings==2.5.2
Requires-Dist: python-dotenv==1.0.1
Requires-Dist: redis>=5.0.1
Requires-Dist: httpx>=0.25.0
Requires-Dist: aiofiles>=23.2.1
Requires-Dist: orjson>=3.9.7
Requires-Dist: typing-extensions>=4.8.0
Requires-Dist: python-multipart>=0.0.6
Requires-Dist: email-validator>=2.1.0
Requires-Dist: python-jose[cryptography]>=3.3.0
Requires-Dist: passlib[bcrypt]>=1.7.4
Requires-Dist: sqlalchemy>=2.0.0
Requires-Dist: alembic>=1.13.0
Requires-Dist: asyncpg>=0.29.0
Requires-Dist: loguru>=0.7.2
Requires-Dist: prometheus-client>=0.17.1
Provides-Extra: dev
Requires-Dist: pytest>=7.4.0; extra == "dev"
Requires-Dist: pytest-asyncio>=0.21.0; extra == "dev"
Requires-Dist: pytest-cov>=4.1.0; extra == "dev"
Requires-Dist: pytest-xdist>=3.3.1; extra == "dev"
Requires-Dist: pytest-mock>=3.11.1; extra == "dev"
Requires-Dist: httpx[test]>=0.25.0; extra == "dev"
Requires-Dist: black>=23.12.0; extra == "dev"
Requires-Dist: isort>=5.13.0; extra == "dev"
Requires-Dist: flake8>=6.1.0; extra == "dev"
Requires-Dist: bandit>=1.7.5; extra == "dev"
Requires-Dist: pre-commit>=3.6.0; extra == "dev"
Requires-Dist: ipython>=8.18.0; extra == "dev"
Requires-Dist: ipdb>=0.13.13; extra == "dev"
Requires-Dist: rich>=13.7.0; extra == "dev"
Requires-Dist: watchfiles>=0.21.0; extra == "dev"
Provides-Extra: ai
Requires-Dist: google-generativeai>=0.3.0; extra == "ai"
Requires-Dist: openai>=1.3.0; extra == "ai"
Requires-Dist: anthropic>=0.7.0; extra == "ai"
Requires-Dist: boto3>=1.29.0; extra == "ai"
Provides-Extra: cloud
Requires-Dist: google-cloud-storage>=2.10.0; extra == "cloud"
Requires-Dist: google-cloud-tasks>=2.14.0; extra == "cloud"
Provides-Extra: docs
Requires-Dist: mkdocs>=1.5.3; extra == "docs"
Requires-Dist: mkdocs-material>=9.4.8; extra == "docs"
Requires-Dist: mkdocs-mermaid2-plugin>=1.1.1; extra == "docs"
Provides-Extra: all
Requires-Dist: px-rfs-project[ai,cloud,dev,docs]; extra == "all"
